tablemango/__init__.py
tablemango/tablemango.py
tablemango-0.2.dist-info/LICENSE
tablemango-0.2.dist-info/METADATA
tablemango-0.2.dist-info/WHEEL
tablemango-0.2.dist-info/top_level.txt
tablemango-0.2.dist-info/RECORD
